{
    "total": [
        {
            "id": "100018593553060",
            "count": 0
        },
        {
            "id": "100029384528916",
            "count": 0
        },
        {
            "id": "100030050475161",
            "count": 33
        },
        {
            "id": "100035912542034",
            "count": 1553
        },
        {
            "id": "100042742523255",
            "count": 27
        },
        {
            "id": "100043131636429",
            "count": 677
        },
        {
            "id": "100048421869521",
            "count": 5
        },
        {
            "id": "100049074306712",
            "count": 159
        },
        {
            "id": "100054799780320",
            "count": 206
        },
        {
            "id": "100054823718641",
            "count": 1
        },
        {
            "id": "100055341733190",
            "count": 160
        },
        {
            "id": "100062255102630",
            "count": 12
        },
        {
            "id": "100064648747634",
            "count": 950
        },
        {
            "id": "100068530164402",
            "count": 0
        },
        {
            "id": "100069011317482",
            "count": 0
        },
        {
            "id": "100072302162723",
            "count": 0
        },
        {
            "id": "100072334008737",
            "count": 0
        },
        {
            "id": "100073809054102",
            "count": 0
        },
        {
            "id": "100074028920631",
            "count": 51
        },
        {
            "id": "100074414866926",
            "count": 1108
        },
        {
            "id": "100075303349928",
            "count": 0
        },
        {
            "id": "100075312850012",
            "count": 743
        },
        {
            "id": "100076462077010",
            "count": 0
        },
        {
            "id": "100076599194930",
            "count": 8
        },
        {
            "id": "100076630042143",
            "count": 3
        },
        {
            "id": "100077128012202",
            "count": 3671
        },
        {
            "id": "100078436167159",
            "count": 0
        },
        {
            "id": "100082131182979",
            "count": 2973
        },
        {
            "id": "100076603483763",
            "count": 1
        }
    ],
    "week": [
        {
            "id": "100018593553060",
            "count": 0,
            "name": "Người dùng facebook"
        },
        {
            "id": "100029384528916",
            "count": 0,
            "name": "Người dùng facebook"
        },
        {
            "id": "100030050475161",
            "count": 0,
            "name": "Người dùng facebook"
        },
        {
            "id": "100035912542034",
            "count": 0,
            "name": "Người dùng facebook"
        },
        {
            "id": "100042742523255",
            "count": 0,
            "name": "Người dùng facebook"
        },
        {
            "id": "100043131636429",
            "count": 0,
            "name": "Người dùng facebook"
        },
        {
            "id": "100048421869521",
            "count": 0,
            "name": "Người dùng facebook"
        },
        {
            "id": "100049074306712",
            "count": 0,
            "name": "Người dùng facebook"
        },
        {
            "id": "100054799780320",
            "count": 0,
            "name": "Người dùng facebook"
        },
        {
            "id": "100054823718641",
            "count": 0,
            "name": "Người dùng facebook"
        },
        {
            "id": "100055341733190",
            "count": 0,
            "name": "Người dùng facebook"
        },
        {
            "id": "100062255102630",
            "count": 0,
            "name": "Người dùng facebook"
        },
        {
            "id": "100064648747634",
            "count": 0,
            "name": "Người dùng facebook"
        },
        {
            "id": "100068530164402",
            "count": 0,
            "name": "Người dùng facebook"
        },
        {
            "id": "100069011317482",
            "count": 0,
            "name": "Người dùng facebook"
        },
        {
            "id": "100072302162723",
            "count": 0,
            "name": "Người dùng facebook"
        },
        {
            "id": "100072334008737",
            "count": 0,
            "name": "Người dùng facebook"
        },
        {
            "id": "100073809054102",
            "count": 0,
            "name": "Người dùng facebook"
        },
        {
            "id": "100074028920631",
            "count": 0,
            "name": "Người dùng facebook"
        },
        {
            "id": "100074414866926",
            "count": 0,
            "name": "Người dùng facebook"
        },
        {
            "id": "100075303349928",
            "count": 0,
            "name": "Người dùng facebook"
        },
        {
            "id": "100075312850012",
            "count": 0,
            "name": "Người dùng facebook"
        },
        {
            "id": "100076462077010",
            "count": 0,
            "name": "Người dùng facebook"
        },
        {
            "id": "100076599194930",
            "count": 0,
            "name": "Người dùng facebook"
        },
        {
            "id": "100076630042143",
            "count": 0,
            "name": "Người dùng facebook"
        },
        {
            "id": "100077128012202",
            "count": 0,
            "name": "Người dùng facebook"
        },
        {
            "id": "100078436167159",
            "count": 0,
            "name": "Người dùng facebook"
        },
        {
            "id": "100082131182979",
            "count": 0,
            "name": "Người dùng facebook"
        },
        {
            "id": "100076603483763",
            "count": 0,
            "name": "Người dùng facebook"
        }
    ],
    "day": [
        {
            "id": "100018593553060",
            "count": 0,
            "name": "Người dùng facebook"
        },
        {
            "id": "100029384528916",
            "count": 0,
            "name": "Người dùng facebook"
        },
        {
            "id": "100030050475161",
            "count": 0,
            "name": "Người dùng facebook"
        },
        {
            "id": "100035912542034",
            "count": 0,
            "name": "Người dùng facebook"
        },
        {
            "id": "100042742523255",
            "count": 0,
            "name": "Người dùng facebook"
        },
        {
            "id": "100043131636429",
            "count": 0,
            "name": "Người dùng facebook"
        },
        {
            "id": "100048421869521",
            "count": 0,
            "name": "Người dùng facebook"
        },
        {
            "id": "100049074306712",
            "count": 0,
            "name": "Người dùng facebook"
        },
        {
            "id": "100054799780320",
            "count": 0,
            "name": "Người dùng facebook"
        },
        {
            "id": "100054823718641",
            "count": 0,
            "name": "Người dùng facebook"
        },
        {
            "id": "100055341733190",
            "count": 0,
            "name": "Người dùng facebook"
        },
        {
            "id": "100062255102630",
            "count": 0,
            "name": "Người dùng facebook"
        },
        {
            "id": "100064648747634",
            "count": 0,
            "name": "Người dùng facebook"
        },
        {
            "id": "100068530164402",
            "count": 0,
            "name": "Người dùng facebook"
        },
        {
            "id": "100069011317482",
            "count": 0,
            "name": "Người dùng facebook"
        },
        {
            "id": "100072302162723",
            "count": 0,
            "name": "Người dùng facebook"
        },
        {
            "id": "100072334008737",
            "count": 0,
            "name": "Người dùng facebook"
        },
        {
            "id": "100073809054102",
            "count": 0,
            "name": "Người dùng facebook"
        },
        {
            "id": "100074028920631",
            "count": 0,
            "name": "Người dùng facebook"
        },
        {
            "id": "100074414866926",
            "count": 0,
            "name": "Người dùng facebook"
        },
        {
            "id": "100075303349928",
            "count": 0,
            "name": "Người dùng facebook"
        },
        {
            "id": "100075312850012",
            "count": 0,
            "name": "Người dùng facebook"
        },
        {
            "id": "100076462077010",
            "count": 0,
            "name": "Người dùng facebook"
        },
        {
            "id": "100076599194930",
            "count": 0,
            "name": "Người dùng facebook"
        },
        {
            "id": "100076630042143",
            "count": 0,
            "name": "Người dùng facebook"
        },
        {
            "id": "100077128012202",
            "count": 0,
            "name": "Người dùng facebook"
        },
        {
            "id": "100078436167159",
            "count": 0,
            "name": "Người dùng facebook"
        },
        {
            "id": "100082131182979",
            "count": 0,
            "name": "Người dùng facebook"
        },
        {
            "id": "100076603483763",
            "count": 0,
            "name": "Người dùng facebook"
        }
    ],
    "time": 0
}